Metadata-Version: 2.1
Name: YassineLr
Version: 1.0.2
Summary: An awesome package to replace humans
Home-page: http://pypi.python.org/pypi/YassineLr/
Author: Phues
Author-email: yl.benyamina@esi-sba.dz
License: LICENSE.txt
License-File: LICENSE.txt
